Metadata-Version: 1.1
Name: trialPy
Version: 0.0.1
Summary: A very basic calculator
Home-page: UNKNOWN
Author: Sanjay Saifi
Author-email: ucanwhatsappme@gmail.com
License: MIT
Keywords: calculator
Platform: UNKNOWN
Classifier: Development Status :: 5 - Production/Stable
Classifier: Intended Audience :: Education
Classifier: Operating System :: Microsoft :: Windows :: Windows 8
Classifier: License :: OSI Approved :: MIT License
Classifier: Programming Language :: Python :: 3
